lit_commit_cb.py
lit_commit_cb-0.0.1.dist-info/METADATA
lit_commit_cb-0.0.1.dist-info/WHEEL
lit_commit_cb-0.0.1.dist-info/top_level.txt
lit_commit_cb-0.0.1.dist-info/RECORD
